<?xml version="1.0" encoding="UTF-8"?>
<datasources>
  <xa-datasource jndi-name="java:jboss/datasources/TestDS" pool-name="TestDS" enabled="true">
      <xa-datasource-property name="ServerName">localhost</xa-datasource-property>  
      <xa-datasource-property name="PortNumber">5432</xa-datasource-property>  
      <xa-datasource-property name="DatabaseName">crashrec</xa-datasource-property>  
      <xa-datasource-class>org.postgresql.xa.PGXADataSource</xa-datasource-class>
      <driver>jdbc-driver.jar</driver>
      
      <validation>
        <validate-on-match>true</validate-on-match>
        <valid-connection-checker class-name="org.jboss.jca.adapters.jdbc.extensions.postgres.PostgreSQLValidConnectionChecker" />
        <exception-sorter class-name="org.jboss.jca.adapters.jdbc.extensions.postgres.PostgreSQLExceptionSorter" />
      </validation>
      
      <security>
          <user-name>crashrec</user-name>
          <password>crashrec</password>
      </security>      
  </xa-datasource>
</datasources>
